wayback_scraper/__init__.py
wayback_scraper/wayback_scraper.py
wayback_scraper-1.2.dist-info/LICENSE
wayback_scraper-1.2.dist-info/METADATA
wayback_scraper-1.2.dist-info/WHEEL
wayback_scraper-1.2.dist-info/entry_points.txt
wayback_scraper-1.2.dist-info/top_level.txt
wayback_scraper-1.2.dist-info/RECORD
