Metadata-Version: 2.1
Name: wayback-scraper
Version: 1.2
Summary: A command line utility for scraping wayback snapshots from archive.org.
Home-page: https://github.com/chocolatebrown/wayback_scraper
Author: Ramaswamy Venkatachalam
Author-email: ramasamynasa@gmail.com
License: MIT
Platform: UNKNOWN
Classifier: Development Status :: 5 - Production/Stable
Classifier: Programming Language :: Python :: 3.6
Classifier: Topic :: Utilities
Classifier: License :: OSI Approved :: MIT License
Classifier: Operating System :: OS Independent
